MANIFEST.in
README.md
setup.py
mv_logger/__init__.py
mv_logger/logstash.py
mv_logger.egg-info/PKG-INFO
mv_logger.egg-info/SOURCES.txt
mv_logger.egg-info/dependency_links.txt
mv_logger.egg-info/requires.txt
mv_logger.egg-info/top_level.txt