Metadata-Version: 1.1
Name: mv-logger
Version: 0.0.3
Summary: mv-logger
Home-page: https://github.com/willard-ag/mv-logger
Author: Mobile Vikings PL
Author-email: kontakt@mobilevikings.pl
License: MIT
Platform: UNKNOWN
Classifier: Intended Audience :: Developers
Classifier: Programming Language :: Python
Classifier: Operating System :: OS Independent
Classifier: Environment :: Web Environment
